pylogrotate/__init__.py
pylogrotate/main.py
pylogrotate-1.1.0.dist-info/LICENSE
pylogrotate-1.1.0.dist-info/METADATA
pylogrotate-1.1.0.dist-info/WHEEL
pylogrotate-1.1.0.dist-info/entry_points.txt
pylogrotate-1.1.0.dist-info/top_level.txt
pylogrotate-1.1.0.dist-info/RECORD
