Metadata-Version: 2.1
Name: pylogrotate
Version: 1.1.0
Summary: Logrotate in Python
Home-page: https://github.com/xiachufang/pylogrotate
Author: gfreezy
Author-email: gfreezy@gmail.com
License: MIT
Keywords: logrotate
Classifier: Development Status :: 3 - Alpha
Classifier: License :: OSI Approved :: MIT License
Classifier: Natural Language :: Chinese (Simplified)
Classifier: Programming Language :: Python :: 3
Classifier: Programming Language :: Python :: 3.6
Classifier: Programming Language :: Python :: 3.7
Classifier: Programming Language :: Python :: 3.8
Classifier: Programming Language :: Python :: 3.9
Classifier: Programming Language :: Python :: 3.10
Classifier: Programming Language :: Python :: 3.11
Classifier: Programming Language :: Python :: 3.12
Classifier: Programming Language :: Python :: 3 :: Only
License-File: LICENSE
Requires-Dist: pyyaml
Requires-Dist: hdfs
Requires-Dist: pqueue
Provides-Extra: test
Requires-Dist: pytest ; extra == 'test'
Requires-Dist: freezegun ; extra == 'test'
Requires-Dist: zstandard ; extra == 'test'
